ansys/api/tools/filetransfer/VERSION
ansys/api/tools/filetransfer/__init__.py
ansys/api/tools/filetransfer/py.typed
ansys/api/tools/filetransfer/v1/file_transfer_service.proto
ansys/api/tools/filetransfer/v1/file_transfer_service_pb2.py
ansys/api/tools/filetransfer/v1/file_transfer_service_pb2.pyi
ansys/api/tools/filetransfer/v1/file_transfer_service_pb2_grpc.py
ansys/api/tools/filetransfer/v1/file_transfer_service_pb2_grpc.pyi
ansys_api_tools_filetransfer-0.1.1.dist-info/AUTHORS
ansys_api_tools_filetransfer-0.1.1.dist-info/LICENSE
ansys_api_tools_filetransfer-0.1.1.dist-info/METADATA
ansys_api_tools_filetransfer-0.1.1.dist-info/WHEEL
ansys_api_tools_filetransfer-0.1.1.dist-info/entry_points.txt
ansys_api_tools_filetransfer-0.1.1.dist-info/top_level.txt
ansys_api_tools_filetransfer-0.1.1.dist-info/RECORD
