Metadata-Version: 2.1
Name: ansys-api-tools-filetransfer
Version: 0.1.1
Summary: Autogenerated python gRPC interface package for ansys-api-tools-filetransfer.
Home-page: https://github.com/ansys/ansys-api-tools-filetransfer
Author: ANSYS, Inc.
Author-email: pyansys.core@ansys.com
License: MIT
Project-URL: Documentation, https://github.com/ansys/ansys-api-tools-filetransfer/#readme
Project-URL: Source, https://github.com/ansys/ansys-api-tools-filetransfer/
Project-URL: Tracker, https://github.com/ansys/ansys-api-tools-filetransfer/issues/
Requires-Python: >=3.7
License-File: LICENSE
License-File: AUTHORS
Requires-Dist: grpcio~=1.17
Requires-Dist: protobuf<6,>=3.19
